gpforecaster/__init__.py
gpforecaster/model/__init__.py
gpforecaster/model/gp.py
gpforecaster/model/gpf.py
gpforecaster/model/hyperparameter_tuning.py
gpforecaster/model/mean_functions.py
gpforecaster/model/mlls.py
gpforecaster/results/__init__.py
gpforecaster/results/calculate_metrics.py
gpforecaster/tests/__init__.py
gpforecaster/tests/test_calculate_results.py
gpforecaster/tests/test_early_stopping.py
gpforecaster/tests/test_hyperparameter_tuning.py
gpforecaster/tests/test_hyperparameter_tuning_gptype_percent.py
gpforecaster/tests/test_hyperparameter_tuning_m5.py
gpforecaster/tests/test_model_results_m5.py
gpforecaster/tests/test_model_results_police.py
gpforecaster/tests/test_model_results_prison.py
gpforecaster/tests/test_run_model_with_sampled_dataset.py
gpforecaster/tests/test_sparse_gps.py
gpforecaster/tests/test_store_results.py
gpforecaster/tests/test_svg_gps.py
gpforecaster/tests/test_tourism_gpf_with_local_file.py
gpforecaster/utils/__init__.py
gpforecaster/utils/logger.py
gpforecaster/utils/loss_function.py
gpforecaster/visualization/__init__.py
gpforecaster/visualization/plot_predictions.py
gpforecaster-0.3.142.dist-info/LICENCE
gpforecaster-0.3.142.dist-info/METADATA
gpforecaster-0.3.142.dist-info/WHEEL
gpforecaster-0.3.142.dist-info/top_level.txt
gpforecaster-0.3.142.dist-info/RECORD
